ndscheduler/__init__.py
ndscheduler/constants.py
ndscheduler/default_settings.py
ndscheduler/default_settings_test.py
ndscheduler/job.py
ndscheduler/utils.py
ndscheduler/utils_test.py
ndscheduler/version.py
ndscheduler/core/__init__.py
ndscheduler/core/scheduler_manager.py
ndscheduler/core/scheduler_manager_test.py
ndscheduler/core/datastore/__init__.py
ndscheduler/core/datastore/tables.py
ndscheduler/core/datastore/providers/__init__.py
ndscheduler/core/datastore/providers/base.py
ndscheduler/core/datastore/providers/base_test.py
ndscheduler/core/datastore/providers/mysql.py
ndscheduler/core/datastore/providers/postgresql.py
ndscheduler/core/datastore/providers/sqlite.py
ndscheduler/core/scheduler/__init__.py
ndscheduler/core/scheduler/base.py
ndscheduler/core/scheduler/base_test.py
ndscheduler/server/__init__.py
ndscheduler/server/server.py
ndscheduler/server/handlers/__init__.py
ndscheduler/server/handlers/audit_logs.py
ndscheduler/server/handlers/base.py
ndscheduler/server/handlers/executions.py
ndscheduler/server/handlers/executions_test.py
ndscheduler/server/handlers/index.py
ndscheduler/server/handlers/jobs.py
ndscheduler/server/handlers/jobs_test.py
ndscheduler/static/index.html
ndscheduler/static/css/main.css
ndscheduler/static/css/vendor/bootstrap-switch.css
ndscheduler/static/css/vendor/bootstrap.css
ndscheduler/static/css/vendor/bootstrap.css.map
ndscheduler/static/css/vendor/jquery.dataTables.css
ndscheduler/static/css/vendor/select2-bootstrap.css
ndscheduler/static/css/vendor/select2.css
ndscheduler/static/css/vendor/images/Sorting icons.psd
ndscheduler/static/css/vendor/images/back_disabled.png
ndscheduler/static/css/vendor/images/back_enabled.png
ndscheduler/static/css/vendor/images/back_enabled_hover.png
ndscheduler/static/css/vendor/images/favicon.ico
ndscheduler/static/css/vendor/images/forward_disabled.png
ndscheduler/static/css/vendor/images/forward_enabled.png
ndscheduler/static/css/vendor/images/forward_enabled_hover.png
ndscheduler-0.3.0.dist-info/LICENSE.txt
ndscheduler-0.3.0.dist-info/METADATA
ndscheduler-0.3.0.dist-info/WHEEL
ndscheduler-0.3.0.dist-info/top_level.txt
ndscheduler-0.3.0.dist-info/RECORD
