Metadata-Version: 2.1
Name: ndscheduler
Version: 0.3.0
Summary: ndscheduler: A cron-replacement library from Nextdoor
Home-page: https://github.com/Nextdoor/ndscheduler
Author: Nextdoor Engineering
Author-email: eng@nextdoor.com
License: Apache License, Version 2
Download-URL: http://pypi.python.org/pypi/ndscheduler#downloads
Keywords: scheduler nextdoor cron python
Platform: UNKNOWN
Classifier: Development Status :: 5 - Production/Stable
Classifier: License :: OSI Approved :: BSD License
Classifier: Topic :: System :: Distributed Computing
Classifier: Topic :: Software Development :: Object Brokering
Classifier: Programming Language :: Python
Classifier: Programming Language :: Python :: 2.7
Classifier: Programming Language :: Python :: 3.3
Classifier: Programming Language :: Python :: 3.4
Classifier: Programming Language :: Python :: 3.5
Classifier: Programming Language :: Python :: 3.6
Classifier: Programming Language :: Python :: Implementation :: CPython
Classifier: Operating System :: OS Independent
Requires-Dist: APScheduler (==3.0.0)
Requires-Dist: SQLAlchemy (==1.0.0)
Requires-Dist: future (==0.15.2)
Requires-Dist: tornado (==4.3.0)
Requires-Dist: python-dateutil (==2.2)
Provides-Extra: python_version_3.3_
Requires-Dist: funcsigs ; extra == 'python_version_3.3_'
